ydsdk/__init__.py
ydsdk-0.2.6.dist-info/LICENSE
ydsdk-0.2.6.dist-info/METADATA
ydsdk-0.2.6.dist-info/WHEEL
ydsdk-0.2.6.dist-info/top_level.txt
ydsdk-0.2.6.dist-info/RECORD
