Metadata-Version: 2.1
Name: ydsdk
Version: 0.2.6
Summary: Yundun Api Sdk For Python
Home-page: https://github.com/pypa/sdk_python
Author: lideqiang
Author-email: lideqiang@yundun.com
License: UNKNOWN
Platform: UNKNOWN
Classifier: Programming Language :: Python :: 3
Classifier: License :: OSI Approved :: MIT License
Requires-Python: >=3.5
License-File: LICENSE
